ediclean/__init__.py
ediclean/__main__.py
ediclean/paxlst.py
ediclean-0.1.4.dist-info/METADATA
ediclean-0.1.4.dist-info/WHEEL
ediclean-0.1.4.dist-info/entry_points.txt
ediclean-0.1.4.dist-info/top_level.txt
ediclean-0.1.4.dist-info/RECORD
