Metadata-Version: 2.1
Name: ediclean
Version: 0.1.4
Summary: A Python package to strip non-standard text blocks from UN/EDIFACT messages.
Home-page: https://github.com/goOICT/ediclean
Author: Zoltan Janota
Author-email: zoltan.janota@un.org
License: UNKNOWN
Project-URL: Bug Reports, https://github.com/goOICT/ediclean/issues
Project-URL: Source, https://github.com/goOICT/ediclean
Keywords: paxlst edifact un/edifact
Platform: UNKNOWN
Classifier: Development Status :: 3 - Alpha
Classifier: Intended Audience :: Developers
Classifier: Topic :: Text Processing
Classifier: License :: OSI Approved :: MIT License
Classifier: Programming Language :: Python :: 3
Requires-Python: >=3.4
